setup.cfg
setup.py
puREST.egg-info/PKG-INFO
puREST.egg-info/SOURCES.txt
puREST.egg-info/dependency_links.txt
puREST.egg-info/requires.txt
puREST.egg-info/top_level.txt
purest/__init__.py