Metadata-Version: 1.0
Name: puREST
Version: 0.0.1.post1
Summary: Simple dynamic REST consumer
Home-page: https://github.com/vlasy/purest
Author: Michal Vlasák
Author-email: daeatel@gmail.com
License: MIT
Platform: UNKNOWN
